CHANGELOG.rst
LICENSE
MANIFEST.in
README.rst
setup.cfg
setup.py
tox.ini
Mopidy.OrangePi.Pidi.egg-info/PKG-INFO
Mopidy.OrangePi.Pidi.egg-info/SOURCES.txt
Mopidy.OrangePi.Pidi.egg-info/dependency_links.txt
Mopidy.OrangePi.Pidi.egg-info/entry_points.txt
Mopidy.OrangePi.Pidi.egg-info/not-zip-safe
Mopidy.OrangePi.Pidi.egg-info/requires.txt
Mopidy.OrangePi.Pidi.egg-info/top_level.txt
mopidy_orangepi_pidi/__init__.py
mopidy_orangepi_pidi/brainz.py
mopidy_orangepi_pidi/ext.conf
mopidy_orangepi_pidi/frontend.py
mopidy_orangepi_pidi/plugin.py
tests/__init__.py
tests/dummy_audio.py
tests/dummy_backend.py
tests/dummy_mixer.py
tests/test_extension.py
tests/test_frontend.py